{
  "name": "Carladevv.com",
  "tagline": "desarrollando herramientas web para videojuegos, ciencia y educación",
  "bioTab": "Mi trayectoria",
  "bioIntro": "Me gusta estar en un estado de cambio constante, buscando siempre profundizar en todo aquello con lo que me cruzo. Mi objetivo es usar mis habilidades para ayudar a construir un mundo mejor.",
  "recentReadsTitle": "Lecturas recientes",
  "recentReadsSubtitle": "---",
  "techStack": "Tecnologías",
  "viewLink": "Ver proyecto",
  "moreMedia": "Más multimedia",
  "language": "Idioma",
  "fontSize": "Tamaño de fuente",
  "footerNote": "Código del portafolio en GitHub",
  "sections": {
    "graphics": "Gráficos",
    "accessibility": "Accesibilidad",
    "tooling": "Herramientas",
    "archaeology": "Arqueología",
    "science": "Ciencia",
    "bio": "Trayectoria"
  },
  "links": {
    "trySite": "Probar sitio",
    "readArticle": "Leer artículo",
    "githubRepo": "Repositorio en GitHub",
    "chromeWebStore": "Chrome Web Store",
    "firefoxAddons": "Complementos de Firefox"
  }
}